pub_analyzer/__init__.py
pub_analyzer/__main__.py
pub_analyzer/css/body.tcss
pub_analyzer/css/buttons.tcss
pub_analyzer/css/checkbox.tcss
pub_analyzer/css/collapsible.tcss
pub_analyzer/css/datatable.tcss
pub_analyzer/css/editor.tcss
pub_analyzer/css/main.tcss
pub_analyzer/css/report.tcss
pub_analyzer/css/search.tcss
pub_analyzer/css/summary.tcss
pub_analyzer/css/tabs.tcss
pub_analyzer/css/tree.tcss
pub_analyzer/internal/__init__.py
pub_analyzer/internal/identifier.py
pub_analyzer/internal/limiter.py
pub_analyzer/internal/render.py
pub_analyzer/internal/report.py
pub_analyzer/internal/templates/author_report.typ
pub_analyzer/main.py
pub_analyzer/models/__init__.py
pub_analyzer/models/author.py
pub_analyzer/models/concept.py
pub_analyzer/models/institution.py
pub_analyzer/models/report.py
pub_analyzer/models/source.py
pub_analyzer/models/topic.py
pub_analyzer/models/work.py
pub_analyzer/widgets/__init__.py
pub_analyzer/widgets/author/__init__.py
pub_analyzer/widgets/author/cards.py
pub_analyzer/widgets/author/core.py
pub_analyzer/widgets/author/tables.py
pub_analyzer/widgets/body.py
pub_analyzer/widgets/common/__init__.py
pub_analyzer/widgets/common/card.py
pub_analyzer/widgets/common/filesystem.py
pub_analyzer/widgets/common/filters.py
pub_analyzer/widgets/common/input.py
pub_analyzer/widgets/common/label.py
pub_analyzer/widgets/common/modal.py
pub_analyzer/widgets/common/selector.py
pub_analyzer/widgets/common/summary.py
pub_analyzer/widgets/institution/__init__.py
pub_analyzer/widgets/institution/cards.py
pub_analyzer/widgets/institution/core.py
pub_analyzer/widgets/institution/tables.py
pub_analyzer/widgets/report/__init__.py
pub_analyzer/widgets/report/author.py
pub_analyzer/widgets/report/cards.py
pub_analyzer/widgets/report/concept.py
pub_analyzer/widgets/report/core.py
pub_analyzer/widgets/report/editor.py
pub_analyzer/widgets/report/export.py
pub_analyzer/widgets/report/grants.py
pub_analyzer/widgets/report/institution.py
pub_analyzer-0.5.6.dist-info/METADATA
pub_analyzer-0.5.6.dist-info/WHEEL
pub_analyzer-0.5.6.dist-info/entry_points.txt
pub_analyzer-0.5.6.dist-info/licenses/LICENSE
pub_analyzer-0.5.6.dist-info/RECORD
