Metadata-Version: 2.4
Name: pub-analyzer
Version: 0.5.6
Summary: A text user interface, written in python, which automates the generation of scientific production reports using OpenAlex
License: MIT
License-File: LICENSE
Author: Alejandro Gaspar
Author-email: alejandro@gaspar.land
Maintainer: Alejandro Gaspar
Maintainer-email: alejandro@gaspar.land
Requires-Python: >=3.10,<4.0
Classifier: Development Status :: 3 - Alpha
Classifier: Environment :: Console
Classifier: Intended Audience :: Science/Research
Classifier: License :: OSI Approved :: MIT License
Classifier: Operating System :: MacOS
Classifier: Operating System :: Microsoft :: Windows :: Windows 10
Classifier: Operating System :: Microsoft :: Windows :: Windows 11
Classifier: Operating System :: POSIX :: Linux
Classifier: Programming Language :: Python :: 3
Classifier: Programming Language :: Python :: 3.10
Classifier: Programming Language :: Python :: 3.11
Classifier: Programming Language :: Python :: 3.12
Classifier: Programming Language :: Python :: 3.13
Classifier: Programming Language :: Python :: 3.14
Classifier: Typing :: Typed
Requires-Dist: httpx[http2] (==0.28.1)
Requires-Dist: pydantic (==2.12.5)
Requires-Dist: textual (==0.85.2)
Requires-Dist: typst (==0.13.2)
Project-URL: Documentation, https://pub-analyzer.com/
Project-URL: Homepage, https://github.com/alejandrgaspar/pub-analyzer
Project-URL: Repository, https://github.com/alejandrgaspar/pub-analyzer
